ml_datasets/__init__.py
ml_datasets/_registry.py
ml_datasets/spacy_readers.py
ml_datasets/util.py
ml_datasets/loaders/__init__.py
ml_datasets/loaders/cmu.py
ml_datasets/loaders/dbpedia.py
ml_datasets/loaders/imdb.py
ml_datasets/loaders/mnist.py
ml_datasets/loaders/quora.py
ml_datasets/loaders/reuters.py
ml_datasets/loaders/snli.py
ml_datasets/loaders/stack_exchange.py
ml_datasets/loaders/universal_dependencies.py
ml_datasets/loaders/wikiner.py
ml_datasets-0.2.0.dist-info/LICENSE
ml_datasets-0.2.0.dist-info/METADATA
ml_datasets-0.2.0.dist-info/WHEEL
ml_datasets-0.2.0.dist-info/entry_points.txt
ml_datasets-0.2.0.dist-info/top_level.txt
ml_datasets-0.2.0.dist-info/zip-safe
ml_datasets-0.2.0.dist-info/RECORD
