Metadata-Version: 2.1
Name: ml-datasets
Version: 0.2.0
Summary: Machine Learning dataset loaders
Home-page: https://github.com/explosion/ml-datasets
Author: Explosion
Author-email: contact@explosion.ai
License: MIT
Platform: UNKNOWN
Requires-Python: >=3.6
